{"__total__": 194, "__name__": "doc_121_Anarchists.txt", "in": {"prob": 0.020618556701030927, "count": 4, "pos": [0, 21, 53, 183]}, "the": {"prob": 0.07731958762886598, "count": 15, "pos": [1, 4, 14, 26, 38, 44, 63, 66, 79, 98, 103, 128, 133, 152, 180]}, "open": {"prob": 0.005154639175257732, "count": 1, "pos": [2]}, "scene": {"prob": 0.005154639175257732, "count": 1, "pos": [3]}, "protagonist": {"prob": 0.005154639175257732, "count": 1, "pos": [5]}, "begin": {"prob": 0.010309278350515464, "count": 2, "pos": [6, 40]}, "to": {"prob": 0.05670103092783505, "count": 11, "pos": [7, 41, 59, 92, 117, 122, 137, 165, 167, 177, 190]}, "reminisc": {"prob": 0.005154639175257732, "count": 1, "pos": [8]}, "about": {"prob": 0.005154639175257732, "count": 1, "pos": [9]}, "hi": {"prob": 0.010309278350515464, "count": 2, "pos": [10, 69]}, "youth": {"prob": 0.005154639175257732, "count": 1, "pos": [11]}, "and": {"prob": 0.030927835051546393, "count": 6, "pos": [12, 105, 114, 130, 147, 160]}, "rememb": {"prob": 0.005154639175257732, "count": 1, "pos": [13]}, "day": {"prob": 0.005154639175257732, "count": 1, "pos": [15]}, "he": {"prob": 0.020618556701030927, "count": 4, "pos": [16, 29, 49, 57]}, "wa": {"prob": 0.005154639175257732, "count": 1, "pos": [17]}, "save": {"prob": 0.005154639175257732, "count": 1, "pos": [18]}, "from": {"prob": 0.010309278350515464, "count": 2, "pos": [19, 112]}, "execut": {"prob": 0.005154639175257732, "count": 1, "pos": [20]}, "a": {"prob": 0.03608247422680412, "count": 7, "pos": [22, 35, 73, 89, 163, 184, 191]}, "raid": {"prob": 0.005154639175257732, "count": 1, "pos": [23]}, "perform": {"prob": 0.005154639175257732, "count": 1, "pos": [24]}, "by": {"prob": 0.020618556701030927, "count": 4, "pos": [25, 102, 142, 159]}, "anarchist": {"prob": 0.005154639175257732, "count": 1, "pos": [27]}, "cell": {"prob": 0.005154639175257732, "count": 1, "pos": [28]}, "would": {"prob": 0.005154639175257732, "count": 1, "pos": [30]}, "later": {"prob": 0.010309278350515464, "count": 2, "pos": [31, 50]}, "join": {"prob": 0.005154639175257732, "count": 1, "pos": [32]}, "after": {"prob": 0.005154639175257732, "count": 1, "pos": [33]}, "reach": {"prob": 0.005154639175257732, "count": 1, "pos": [34]}, "safe": {"prob": 0.005154639175257732, "count": 1, "pos": [36]}, "hous": {"prob": 0.005154639175257732, "count": 1, "pos": [37]}, "group": {"prob": 0.015463917525773196, "count": 3, "pos": [39, 129, 153]}, "teach": {"prob": 0.005154639175257732, "count": 1, "pos": [42]}, "him": {"prob": 0.005154639175257732, "count": 1, "pos": [43]}, "trick": {"prob": 0.005154639175257732, "count": 1, "pos": [45]}, "of": {"prob": 0.02577319587628866, "count": 5, "pos": [46, 68, 75, 82, 171]}, "their": {"prob": 0.03608247422680412, "count": 7, "pos": [47, 83, 93, 108, 124, 140, 168]}, "trade": {"prob": 0.005154639175257732, "count": 1, "pos": [48]}, "take": {"prob": 0.005154639175257732, "count": 1, "pos": [51]}, "part": {"prob": 0.005154639175257732, "count": 1, "pos": [52]}, "sever": {"prob": 0.010309278350515464, "count": 2, "pos": [54, 161]}, "mission": {"prob": 0.010309278350515464, "count": 2, "pos": [55, 90]}, "though": {"prob": 0.005154639175257732, "count": 1, "pos": [56]}, "continu": {"prob": 0.005154639175257732, "count": 1, "pos": [58]}, "have": {"prob": 0.005154639175257732, "count": 1, "pos": [60]}, "difficulti": {"prob": 0.005154639175257732, "count": 1, "pos": [61]}, "throughout": {"prob": 0.005154639175257732, "count": 1, "pos": [62]}, "film": {"prob": 0.005154639175257732, "count": 1, "pos": [64]}, "with": {"prob": 0.010309278350515464, "count": 2, "pos": [65, 156]}, "violenc": {"prob": 0.005154639175257732, "count": 1, "pos": [67]}, "new": {"prob": 0.005154639175257732, "count": 1, "pos": [70]}, "job": {"prob": 0.005154639175257732, "count": 1, "pos": [71]}, "eventu": {"prob": 0.005154639175257732, "count": 1, "pos": [72]}, "string": {"prob": 0.005154639175257732, "count": 1, "pos": [74]}, "tragic": {"prob": 0.005154639175257732, "count": 1, "pos": [76]}, "event": {"prob": 0.005154639175257732, "count": 1, "pos": [77]}, "strike": {"prob": 0.010309278350515464, "count": 2, "pos": [78, 178]}, "team": {"prob": 0.005154639175257732, "count": 1, "pos": [80]}, "one": {"prob": 0.005154639175257732, "count": 1, "pos": [81]}, "member": {"prob": 0.005154639175257732, "count": 1, "pos": [84]}, "is": {"prob": 0.005154639175257732, "count": 1, "pos": [85]}, "fatal": {"prob": 0.005154639175257732, "count": 1, "pos": [86]}, "betray": {"prob": 0.005154639175257732, "count": 1, "pos": [87]}, "dure": {"prob": 0.010309278350515464, "count": 2, "pos": [88, 97]}, "lead": {"prob": 0.010309278350515464, "count": 2, "pos": [91, 188]}, "cover": {"prob": 0.005154639175257732, "count": 1, "pos": [94]}, "be": {"prob": 0.005154639175257732, "count": 1, "pos": [95]}, "blown": {"prob": 0.005154639175257732, "count": 1, "pos": [96]}, "next": {"prob": 0.005154639175257732, "count": 1, "pos": [99]}, "now": {"prob": 0.005154639175257732, "count": 1, "pos": [100]}, "want": {"prob": 0.005154639175257732, "count": 1, "pos": [101]}, "japan": {"prob": 0.010309278350515464, "count": 2, "pos": [104, 181]}, "chine": {"prob": 0.005154639175257732, "count": 1, "pos": [106]}, "author": {"prob": 0.005154639175257732, "count": 1, "pos": [107]}, "funder": {"prob": 0.005154639175257732, "count": 1, "pos": [109]}, "turn": {"prob": 0.005154639175257732, "count": 1, "pos": [110]}, "away": {"prob": 0.005154639175257732, "count": 1, "pos": [111]}, "them": {"prob": 0.005154639175257732, "count": 1, "pos": [113]}, "instead": {"prob": 0.005154639175257732, "count": 1, "pos": [115]}, "choo": {"prob": 0.005154639175257732, "count": 1, "pos": [116]}, "support": {"prob": 0.005154639175257732, "count": 1, "pos": [118]}, "socialist": {"prob": 0.005154639175257732, "count": 1, "pos": [119]}, "elector": {"prob": 0.005154639175257732, "count": 1, "pos": [120]}, "polit": {"prob": 0.005154639175257732, "count": 1, "pos": [121]}, "further": {"prob": 0.005154639175257732, "count": 1, "pos": [123]}, "caus": {"prob": 0.005154639175257732, "count": 1, "pos": [125]}, "thi": {"prob": 0.005154639175257732, "count": 1, "pos": [126]}, "anger": {"prob": 0.005154639175257732, "count": 1, "pos": [127]}, "they": {"prob": 0.010309278350515464, "count": 2, "pos": [131, 174]}, "leav": {"prob": 0.005154639175257732, "count": 1, "pos": [132]}, "larger": {"prob": 0.005154639175257732, "count": 1, "pos": [134]}, "organ": {"prob": 0.005154639175257732, "count": 1, "pos": [135]}, "attempt": {"prob": 0.005154639175257732, "count": 1, "pos": [136]}, "surviv": {"prob": 0.005154639175257732, "count": 1, "pos": [138]}, "on": {"prob": 0.005154639175257732, "count": 1, "pos": [139]}, "own": {"prob": 0.005154639175257732, "count": 1, "pos": [141]}, "earn": {"prob": 0.005154639175257732, "count": 1, "pos": [143]}, "money": {"prob": 0.005154639175257732, "count": 1, "pos": [144]}, "through": {"prob": 0.005154639175257732, "count": 1, "pos": [145]}, "gambl": {"prob": 0.005154639175257732, "count": 1, "pos": [146]}, "bank": {"prob": 0.005154639175257732, "count": 1, "pos": [148]}, "robberi": {"prob": 0.005154639175257732, "count": 1, "pos": [149]}, "over": {"prob": 0.005154639175257732, "count": 1, "pos": [150]}, "time": {"prob": 0.005154639175257732, "count": 1, "pos": [151]}, "becom": {"prob": 0.005154639175257732, "count": 1, "pos": [154]}, "agit": {"prob": 0.005154639175257732, "count": 1, "pos": [155]}, "simpli": {"prob": 0.005154639175257732, "count": 1, "pos": [157]}, "scrape": {"prob": 0.005154639175257732, "count": 1, "pos": [158]}, "voic": {"prob": 0.005154639175257732, "count": 1, "pos": [162]}, "desir": {"prob": 0.005154639175257732, "count": 1, "pos": [164]}, "return": {"prob": 0.005154639175257732, "count": 1, "pos": [166]}, "old": {"prob": 0.005154639175257732, "count": 1, "pos": [169]}, "way": {"prob": 0.005154639175257732, "count": 1, "pos": [170]}, "clandestin": {"prob": 0.005154639175257732, "count": 1, "pos": [172]}, "warfar": {"prob": 0.005154639175257732, "count": 1, "pos": [173]}, "collect": {"prob": 0.005154639175257732, "count": 1, "pos": [175]}, "decid": {"prob": 0.005154639175257732, "count": 1, "pos": [176]}, "at": {"prob": 0.005154639175257732, "count": 1, "pos": [179]}, "govern": {"prob": 0.005154639175257732, "count": 1, "pos": [182]}, "high": {"prob": 0.005154639175257732, "count": 1, "pos": [185]}, "profil": {"prob": 0.005154639175257732, "count": 1, "pos": [186]}, "attack": {"prob": 0.005154639175257732, "count": 1, "pos": [187]}, "up": {"prob": 0.005154639175257732, "count": 1, "pos": [189]}, "dramat": {"prob": 0.005154639175257732, "count": 1, "pos": [192]}, "final": {"prob": 0.005154639175257732, "count": 1, "pos": [193]}}