{"__total__": 169, "__name__": "doc_1382_Sunrise_at_Campobello.txt", "begin": {"prob": 0.005917159763313609, "count": 1, "pos": [0]}, "at": {"prob": 0.01775147928994083, "count": 3, "pos": [1, 123, 166]}, "the": {"prob": 0.05917159763313609, "count": 10, "pos": [2, 14, 47, 51, 55, 84, 105, 120, 134, 141]}, "roosevelt": {"prob": 0.01775147928994083, "count": 3, "pos": [3, 155, 160]}, "famili": {"prob": 0.005917159763313609, "count": 1, "pos": [4]}, "vacat": {"prob": 0.005917159763313609, "count": 1, "pos": [5]}, "home": {"prob": 0.005917159763313609, "count": 1, "pos": [6]}, "on": {"prob": 0.01775147928994083, "count": 3, "pos": [7, 46, 133]}, "campobello": {"prob": 0.005917159763313609, "count": 1, "pos": [8]}, "island": {"prob": 0.005917159763313609, "count": 1, "pos": [9]}, "new": {"prob": 0.005917159763313609, "count": 1, "pos": [10]}, "brunswick": {"prob": 0.005917159763313609, "count": 1, "pos": [11]}, "canada": {"prob": 0.005917159763313609, "count": 1, "pos": [12]}, "in": {"prob": 0.023668639053254437, "count": 4, "pos": [13, 21, 50, 104]}, "summer": {"prob": 0.005917159763313609, "count": 1, "pos": [15]}, "of": {"prob": 0.03550295857988166, "count": 6, "pos": [16, 136, 149, 154, 159, 162]}, "1921": {"prob": 0.005917159763313609, "count": 1, "pos": [17]}, "franklin": {"prob": 0.005917159763313609, "count": 1, "pos": [18]}, "is": {"prob": 0.011834319526627219, "count": 2, "pos": [19, 110]}, "depict": {"prob": 0.005917159763313609, "count": 1, "pos": [20]}, "ear": {"prob": 0.005917159763313609, "count": 1, "pos": [22]}, "scene": {"prob": 0.023668639053254437, "count": 4, "pos": [23, 44, 77, 108]}, "as": {"prob": 0.01775147928994083, "count": 3, "pos": [24, 86, 116]}, "vigor": {"prob": 0.005917159763313609, "count": 1, "pos": [25]}, "athlet": {"prob": 0.005917159763313609, "count": 1, "pos": [26]}, "enjoy": {"prob": 0.005917159763313609, "count": 1, "pos": [27]}, "game": {"prob": 0.005917159763313609, "count": 1, "pos": [28]}, "with": {"prob": 0.011834319526627219, "count": 2, "pos": [29, 38]}, "hi": {"prob": 0.04142011834319527, "count": 7, "pos": [30, 34, 58, 61, 65, 96, 137]}, "children": {"prob": 0.005917159763313609, "count": 1, "pos": [31]}, "and": {"prob": 0.05325443786982249, "count": 9, "pos": [32, 40, 64, 89, 99, 132, 143, 153, 158]}, "sail": {"prob": 0.005917159763313609, "count": 1, "pos": [33]}, "boat": {"prob": 0.005917159763313609, "count": 1, "pos": [35]}, "sudden": {"prob": 0.005917159763313609, "count": 1, "pos": [36]}, "stricken": {"prob": 0.005917159763313609, "count": 1, "pos": [37]}, "fever": {"prob": 0.005917159763313609, "count": 1, "pos": [39]}, "then": {"prob": 0.005917159763313609, "count": 1, "pos": [41]}, "paralysi": {"prob": 0.005917159763313609, "count": 1, "pos": [42]}, "subsequ": {"prob": 0.005917159763313609, "count": 1, "pos": [43]}, "focu": {"prob": 0.005917159763313609, "count": 1, "pos": [45]}, "ensu": {"prob": 0.005917159763313609, "count": 1, "pos": [48]}, "conflict": {"prob": 0.005917159763313609, "count": 1, "pos": [49]}, "follow": {"prob": 0.005917159763313609, "count": 1, "pos": [52]}, "week": {"prob": 0.005917159763313609, "count": 1, "pos": [53]}, "between": {"prob": 0.005917159763313609, "count": 1, "pos": [54]}, "bedridden": {"prob": 0.005917159763313609, "count": 1, "pos": [56]}, "fdr": {"prob": 0.023668639053254437, "count": 4, "pos": [57, 72, 79, 109]}, "wife": {"prob": 0.005917159763313609, "count": 1, "pos": [59]}, "eleanor": {"prob": 0.005917159763313609, "count": 1, "pos": [60]}, "mother": {"prob": 0.005917159763313609, "count": 1, "pos": [62]}, "sara": {"prob": 0.005917159763313609, "count": 1, "pos": [63]}, "close": {"prob": 0.005917159763313609, "count": 1, "pos": [66]}, "polit": {"prob": 0.011834319526627219, "count": 2, "pos": [67, 73]}, "advi": {"prob": 0.005917159763313609, "count": 1, "pos": [68]}, "loui": {"prob": 0.005917159763313609, "count": 1, "pos": [69]}, "howe": {"prob": 0.005917159763313609, "count": 1, "pos": [70]}, "over": {"prob": 0.005917159763313609, "count": 1, "pos": [71]}, "futur": {"prob": 0.005917159763313609, "count": 1, "pos": [74]}, "a": {"prob": 0.01775147928994083, "count": 3, "pos": [75, 124, 163]}, "later": {"prob": 0.005917159763313609, "count": 1, "pos": [76]}, "portray": {"prob": 0.005917159763313609, "count": 1, "pos": [78]}, "liter": {"prob": 0.005917159763313609, "count": 1, "pos": [80]}, "drag": {"prob": 0.005917159763313609, "count": 1, "pos": [81]}, "himself": {"prob": 0.005917159763313609, "count": 1, "pos": [82]}, "up": {"prob": 0.005917159763313609, "count": 1, "pos": [83]}, "stair": {"prob": 0.005917159763313609, "count": 1, "pos": [85]}, "through": {"prob": 0.005917159763313609, "count": 1, "pos": [87]}, "grit": {"prob": 0.005917159763313609, "count": 1, "pos": [88]}, "determin": {"prob": 0.005917159763313609, "count": 1, "pos": [90]}, "he": {"prob": 0.011834319526627219, "count": 2, "pos": [91, 117]}, "pain": {"prob": 0.005917159763313609, "count": 1, "pos": [92]}, "strive": {"prob": 0.005917159763313609, "count": 1, "pos": [93]}, "to": {"prob": 0.011834319526627219, "count": 2, "pos": [94, 119]}, "overcom": {"prob": 0.005917159763313609, "count": 1, "pos": [95]}, "physic": {"prob": 0.005917159763313609, "count": 1, "pos": [97]}, "limit": {"prob": 0.005917159763313609, "count": 1, "pos": [98]}, "not": {"prob": 0.005917159763313609, "count": 1, "pos": [100]}, "remain": {"prob": 0.005917159763313609, "count": 1, "pos": [101]}, "an": {"prob": 0.005917159763313609, "count": 1, "pos": [102]}, "invalid": {"prob": 0.005917159763313609, "count": 1, "pos": [103]}, "final": {"prob": 0.005917159763313609, "count": 1, "pos": [106]}, "triumphant": {"prob": 0.005917159763313609, "count": 1, "pos": [107]}, "shown": {"prob": 0.005917159763313609, "count": 1, "pos": [111]}, "re": {"prob": 0.005917159763313609, "count": 1, "pos": [112]}, "enter": {"prob": 0.005917159763313609, "count": 1, "pos": [113]}, "public": {"prob": 0.005917159763313609, "count": 1, "pos": [114]}, "life": {"prob": 0.005917159763313609, "count": 1, "pos": [115]}, "walk": {"prob": 0.005917159763313609, "count": 1, "pos": [118]}, "speaker": {"prob": 0.005917159763313609, "count": 1, "pos": [121]}, "rostrum": {"prob": 0.005917159763313609, "count": 1, "pos": [122]}, "parti": {"prob": 0.005917159763313609, "count": 1, "pos": [125]}, "convent": {"prob": 0.005917159763313609, "count": 1, "pos": [126]}, "aid": {"prob": 0.005917159763313609, "count": 1, "pos": [127]}, "by": {"prob": 0.005917159763313609, "count": 1, "pos": [128]}, "heavi": {"prob": 0.005917159763313609, "count": 1, "pos": [129]}, "leg": {"prob": 0.005917159763313609, "count": 1, "pos": [130]}, "brace": {"prob": 0.005917159763313609, "count": 1, "pos": [131]}, "arm": {"prob": 0.005917159763313609, "count": 1, "pos": [135]}, "eldest": {"prob": 0.005917159763313609, "count": 1, "pos": [138]}, "son": {"prob": 0.005917159763313609, "count": 1, "pos": [139]}, "jame": {"prob": 0.005917159763313609, "count": 1, "pos": [140]}, "play": {"prob": 0.005917159763313609, "count": 1, "pos": [142]}, "film": {"prob": 0.005917159763313609, "count": 1, "pos": [144]}, "both": {"prob": 0.005917159763313609, "count": 1, "pos": [145]}, "omit": {"prob": 0.005917159763313609, "count": 1, "pos": [146]}, "ani": {"prob": 0.005917159763313609, "count": 1, "pos": [147]}, "mention": {"prob": 0.005917159763313609, "count": 1, "pos": [148]}, "warm": {"prob": 0.011834319526627219, "count": 2, "pos": [150, 167]}, "spring": {"prob": 0.011834319526627219, "count": 2, "pos": [151, 168]}, "georgia": {"prob": 0.005917159763313609, "count": 1, "pos": [152]}, "stay": {"prob": 0.005917159763313609, "count": 1, "pos": [156]}, "there": {"prob": 0.005917159763313609, "count": 1, "pos": [157]}, "creation": {"prob": 0.005917159763313609, "count": 1, "pos": [161]}, "rehabilit": {"prob": 0.005917159763313609, "count": 1, "pos": [164]}, "center": {"prob": 0.005917159763313609, "count": 1, "pos": [165]}}