{"__total__": 126, "__name__": "doc_1408_Take_the_Money_and_Run.txt", "virgil": {"prob": 0.007936507936507936, "count": 1, "pos": [0]}, "starkwel": {"prob": 0.015873015873015872, "count": 2, "pos": [1, 111]}, "enter": {"prob": 0.007936507936507936, "count": 1, "pos": [2]}, "a": {"prob": 0.031746031746031744, "count": 4, "pos": [3, 8, 71, 86]}, "life": {"prob": 0.007936507936507936, "count": 1, "pos": [4]}, "of": {"prob": 0.03968253968253968, "count": 5, "pos": [5, 28, 40, 49, 60]}, "crime": {"prob": 0.023809523809523808, "count": 3, "pos": [6, 15, 45]}, "at": {"prob": 0.015873015873015872, "count": 2, "pos": [7, 37]}, "young": {"prob": 0.007936507936507936, "count": 1, "pos": [9]}, "age": {"prob": 0.007936507936507936, "count": 1, "pos": [10]}, "the": {"prob": 0.047619047619047616, "count": 6, "pos": [11, 24, 38, 41, 89, 119]}, "plot": {"prob": 0.007936507936507936, "count": 1, "pos": [12]}, "trace": {"prob": 0.007936507936507936, "count": 1, "pos": [13]}, "hi": {"prob": 0.05555555555555555, "count": 7, "pos": [14, 17, 29, 34, 43, 78, 122]}, "spree": {"prob": 0.007936507936507936, "count": 1, "pos": [16]}, "first": {"prob": 0.007936507936507936, "count": 1, "pos": [18]}, "prison": {"prob": 0.015873015873015872, "count": 2, "pos": [19, 100]}, "term": {"prob": 0.007936507936507936, "count": 1, "pos": [20]}, "and": {"prob": 0.03968253968253968, "count": 5, "pos": [21, 26, 57, 88, 117]}, "eventu": {"prob": 0.015873015873015872, "count": 2, "pos": [22, 35]}, "escap": {"prob": 0.015873015873015872, "count": 2, "pos": [23, 65]}, "birth": {"prob": 0.007936507936507936, "count": 1, "pos": [25]}, "growth": {"prob": 0.007936507936507936, "count": 1, "pos": [27]}, "famili": {"prob": 0.007936507936507936, "count": 1, "pos": [30]}, "as": {"prob": 0.015873015873015872, "count": 2, "pos": [31, 33]}, "well": {"prob": 0.007936507936507936, "count": 1, "pos": [32]}, "captur": {"prob": 0.007936507936507936, "count": 1, "pos": [36]}, "hand": {"prob": 0.007936507936507936, "count": 1, "pos": [39]}, "fbi": {"prob": 0.007936507936507936, "count": 1, "pos": [42]}, "multipl": {"prob": 0.007936507936507936, "count": 1, "pos": [44]}, "includ": {"prob": 0.007936507936507936, "count": 1, "pos": [46]}, "steal": {"prob": 0.007936507936507936, "count": 1, "pos": [47]}, "pain": {"prob": 0.007936507936507936, "count": 1, "pos": [48]}, "glass": {"prob": 0.007936507936507936, "count": 1, "pos": [50]}, "from": {"prob": 0.015873015873015872, "count": 2, "pos": [51, 66]}, "jewer": {"prob": 0.007936507936507936, "count": 1, "pos": [52]}, "store": {"prob": 0.015873015873015872, "count": 2, "pos": [53, 56]}, "rob": {"prob": 0.015873015873015872, "count": 2, "pos": [54, 70]}, "pet": {"prob": 0.007936507936507936, "count": 1, "pos": [55]}, "carv": {"prob": 0.007936507936507936, "count": 1, "pos": [58]}, "bar": {"prob": 0.007936507936507936, "count": 1, "pos": [59]}, "soap": {"prob": 0.007936507936507936, "count": 1, "pos": [61]}, "into": {"prob": 0.007936507936507936, "count": 1, "pos": [62]}, "gun": {"prob": 0.007936507936507936, "count": 1, "pos": [63]}, "to": {"prob": 0.015873015873015872, "count": 2, "pos": [64, 76]}, "jail": {"prob": 0.007936507936507936, "count": 1, "pos": [67]}, "he": {"prob": 0.023809523809523808, "count": 3, "pos": [68, 83, 95]}, "also": {"prob": 0.007936507936507936, "count": 1, "pos": [69]}, "man": {"prob": 0.007936507936507936, "count": 1, "pos": [72]}, "who": {"prob": 0.015873015873015872, "count": 2, "pos": [73, 81]}, "turn": {"prob": 0.007936507936507936, "count": 1, "pos": [74]}, "out": {"prob": 0.007936507936507936, "count": 1, "pos": [75]}, "be": {"prob": 0.007936507936507936, "count": 1, "pos": [77]}, "former": {"prob": 0.007936507936507936, "count": 1, "pos": [79]}, "friend": {"prob": 0.007936507936507936, "count": 1, "pos": [80]}, "reveal": {"prob": 0.007936507936507936, "count": 1, "pos": [82]}, "is": {"prob": 0.007936507936507936, "count": 1, "pos": [84]}, "now": {"prob": 0.007936507936507936, "count": 1, "pos": [85]}, "cop": {"prob": 0.007936507936507936, "count": 1, "pos": [87]}, "movi": {"prob": 0.007936507936507936, "count": 1, "pos": [90]}, "end": {"prob": 0.007936507936507936, "count": 1, "pos": [91]}, "with": {"prob": 0.015873015873015872, "count": 2, "pos": [92, 102]}, "woodi": {"prob": 0.007936507936507936, "count": 1, "pos": [93]}, "admit": {"prob": 0.007936507936507936, "count": 1, "pos": [94]}, "got": {"prob": 0.007936507936507936, "count": 1, "pos": [96]}, "700": {"prob": 0.007936507936507936, "count": 1, "pos": [97]}, "year": {"prob": 0.007936507936507936, "count": 1, "pos": [98]}, "in": {"prob": 0.031746031746031744, "count": 4, "pos": [99, 109, 114, 121]}, "but": {"prob": 0.007936507936507936, "count": 1, "pos": [101]}, "good": {"prob": 0.007936507936507936, "count": 1, "pos": [103]}, "behavior": {"prob": 0.007936507936507936, "count": 1, "pos": [104]}, "can": {"prob": 0.007936507936507936, "count": 1, "pos": [105]}, "get": {"prob": 0.007936507936507936, "count": 1, "pos": [106]}, "that": {"prob": 0.007936507936507936, "count": 1, "pos": [107]}, "cut": {"prob": 0.007936507936507936, "count": 1, "pos": [108]}, "half": {"prob": 0.007936507936507936, "count": 1, "pos": [110]}, "grew": {"prob": 0.007936507936507936, "count": 1, "pos": [112]}, "up": {"prob": 0.007936507936507936, "count": 1, "pos": [113]}, "new": {"prob": 0.007936507936507936, "count": 1, "pos": [115]}, "jersey": {"prob": 0.007936507936507936, "count": 1, "pos": [116]}, "play": {"prob": 0.007936507936507936, "count": 1, "pos": [118]}, "cello": {"prob": 0.007936507936507936, "count": 1, "pos": [120]}, "town": {"prob": 0.007936507936507936, "count": 1, "pos": [123]}, "march": {"prob": 0.007936507936507936, "count": 1, "pos": [124]}, "band": {"prob": 0.007936507936507936, "count": 1, "pos": [125]}}